{
	"format_version": "1.21.11",
	"credit": "Made with Blockbench",
	"texture_size": [64, 64],
	"textures": {
		"2": "item/dsp/wirless_screen",
		"particle": "item/dsp/wirless_screen"
	},
	"elements": [
		{
			"name": "screen",
			"from": [0, 0, 4],
			"to": [15, 1, 13],
			"rotation": {"angle": 0, "axis": "y", "origin": [8, 0, 14]},
			"faces": {
				"north": {"uv": [2.5, 2.25, 6.25, 2.5], "texture": "#2"},
				"east": {"uv": [0.25, 2.25, 2.5, 2.5], "texture": "#2"},
				"south": {"uv": [8.5, 2.25, 12.25, 2.5], "texture": "#2"},
				"west": {"uv": [6.25, 2.25, 8.5, 2.5], "texture": "#2"},
				"up": {"uv": [6.25, 2.25, 2.5, 0], "texture": "#2"},
				"down": {"uv": [10, 0, 6.25, 2.25], "texture": "#2"}
			}
		},
		{
			"from": [0, 1, 4],
			"to": [1, 1.15, 13],
			"rotation": {"angle": 0, "axis": "y", "origin": [0, 1, 4]},
			"faces": {
				"north": {"uv": [6.5, 10.25, 6.75, 10.25], "texture": "#2"},
				"east": {"uv": [4.25, 10.25, 6.5, 10.25], "texture": "#2"},
				"south": {"uv": [9, 10.25, 9.25, 10.25], "texture": "#2"},
				"west": {"uv": [6.75, 10.25, 9, 10.25], "texture": "#2"},
				"up": {"uv": [6.75, 10.25, 6.5, 8], "texture": "#2"},
				"down": {"uv": [7, 8, 6.75, 10.25], "texture": "#2"}
			}
		},
		{
			"from": [1, 1, 5],
			"to": [2, 1.15, 18],
			"rotation": {"x": 0, "y": 90, "z": 0, "origin": [1, 1, 5]},
			"faces": {
				"north": {"uv": [6.5, 10.25, 6.75, 10.25], "texture": "#2"},
				"east": {"uv": [3.25, 10.25, 6.5, 10.25], "texture": "#2"},
				"south": {"uv": [10, 10.25, 10.25, 10.25], "texture": "#2"},
				"west": {"uv": [6.75, 10.25, 10, 10.25], "texture": "#2"},
				"up": {"uv": [6.75, 10.25, 6.5, 7], "texture": "#2"},
				"down": {"uv": [7, 7, 6.75, 10.25], "texture": "#2"}
			}
		},
		{
			"from": [1, 1, 13],
			"to": [2, 1.15, 26],
			"rotation": {"x": 0, "y": 90, "z": 0, "origin": [1, 1, 13]},
			"faces": {
				"north": {"uv": [6.5, 10.25, 6.75, 10.25], "texture": "#2"},
				"east": {"uv": [3.25, 10.25, 6.5, 10.25], "texture": "#2"},
				"south": {"uv": [10, 10.25, 10.25, 10.25], "texture": "#2"},
				"west": {"uv": [6.75, 10.25, 10, 10.25], "texture": "#2"},
				"up": {"uv": [6.75, 10.25, 6.5, 7], "texture": "#2"},
				"down": {"uv": [7, 7, 6.75, 10.25], "texture": "#2"}
			}
		},
		{
			"from": [14, 1, 4],
			"to": [15, 1.15, 13],
			"rotation": {"angle": 0, "axis": "y", "origin": [14, 1, 4]},
			"faces": {
				"north": {"uv": [6.5, 10.25, 6.75, 10.25], "texture": "#2"},
				"east": {"uv": [4.25, 10.25, 6.5, 10.25], "texture": "#2"},
				"south": {"uv": [9, 10.25, 9.25, 10.25], "texture": "#2"},
				"west": {"uv": [6.75, 10.25, 9, 10.25], "texture": "#2"},
				"up": {"uv": [6.75, 10.25, 6.5, 8], "texture": "#2"},
				"down": {"uv": [7, 8, 6.75, 10.25], "texture": "#2"}
			}
		},
		{
			"from": [15, 0, 4],
			"to": [15.2, 1, 5],
			"rotation": {"angle": 0, "axis": "y", "origin": [15, 0, 4]},
			"faces": {
				"north": {"uv": [0.75, 7, 0.75, 7.25], "texture": "#2"},
				"east": {"uv": [0.5, 7, 0.75, 7.25], "texture": "#2"},
				"south": {"uv": [1, 7, 1, 7.25], "texture": "#2"},
				"west": {"uv": [0.75, 7, 1, 7.25], "texture": "#2"},
				"up": {"uv": [0.75, 7, 0.75, 6.75], "texture": "#2"},
				"down": {"uv": [0.75, 6.75, 0.75, 7], "texture": "#2"}
			}
		},
		{
			"from": [15, 0, 12],
			"to": [15.2, 1, 13],
			"rotation": {"angle": 0, "axis": "y", "origin": [15, 0, 12]},
			"faces": {
				"north": {"uv": [0.75, 7, 0.75, 7.25], "texture": "#2"},
				"east": {"uv": [0.5, 7, 0.75, 7.25], "texture": "#2"},
				"south": {"uv": [1, 7, 1, 7.25], "texture": "#2"},
				"west": {"uv": [0.75, 7, 1, 7.25], "texture": "#2"},
				"up": {"uv": [0.75, 7, 0.75, 6.75], "texture": "#2"},
				"down": {"uv": [0.75, 6.75, 0.75, 7], "texture": "#2"}
			}
		},
		{
			"from": [0, 0, 13],
			"to": [0.2, 1, 14],
			"rotation": {"x": 0, "y": -180, "z": 0, "origin": [0, 0, 13]},
			"faces": {
				"north": {"uv": [0.75, 7, 0.75, 7.25], "texture": "#2"},
				"east": {"uv": [0.5, 7, 0.75, 7.25], "texture": "#2"},
				"south": {"uv": [1, 7, 1, 7.25], "texture": "#2"},
				"west": {"uv": [0.75, 7, 1, 7.25], "texture": "#2"},
				"up": {"uv": [0.75, 7, 0.75, 6.75], "texture": "#2"},
				"down": {"uv": [0.75, 6.75, 0.75, 7], "texture": "#2"}
			}
		},
		{
			"from": [0, 0, 5],
			"to": [0.2, 1, 6],
			"rotation": {"x": 0, "y": -180, "z": 0, "origin": [0, 0, 5]},
			"faces": {
				"north": {"uv": [0.75, 7, 0.75, 7.25], "texture": "#2"},
				"east": {"uv": [0.5, 7, 0.75, 7.25], "texture": "#2"},
				"south": {"uv": [1, 7, 1, 7.25], "texture": "#2"},
				"west": {"uv": [0.75, 7, 1, 7.25], "texture": "#2"},
				"up": {"uv": [0.75, 7, 0.75, 6.75], "texture": "#2"},
				"down": {"uv": [0.75, 6.75, 0.75, 7], "texture": "#2"}
			}
		},
		{
			"from": [0, 0, 4],
			"to": [0.2, 1, 5],
			"rotation": {"x": 0, "y": 90, "z": 0, "origin": [0, 0, 4]},
			"faces": {
				"north": {"uv": [0.75, 7, 0.75, 7.25], "texture": "#2"},
				"east": {"uv": [0.5, 7, 0.75, 7.25], "texture": "#2"},
				"south": {"uv": [1, 7, 1, 7.25], "texture": "#2"},
				"west": {"uv": [0.75, 7, 1, 7.25], "texture": "#2"},
				"up": {"uv": [0.75, 7, 0.75, 6.75], "texture": "#2"},
				"down": {"uv": [0.75, 6.75, 0.75, 7], "texture": "#2"}
			}
		},
		{
			"from": [14, 0, 4],
			"to": [14.2, 1, 5],
			"rotation": {"x": 0, "y": 90, "z": 0, "origin": [14, 0, 4]},
			"faces": {
				"north": {"uv": [0.75, 7, 0.75, 7.25], "texture": "#2"},
				"east": {"uv": [0.5, 7, 0.75, 7.25], "texture": "#2"},
				"south": {"uv": [1, 7, 1, 7.25], "texture": "#2"},
				"west": {"uv": [0.75, 7, 1, 7.25], "texture": "#2"},
				"up": {"uv": [0.75, 7, 0.75, 6.75], "texture": "#2"},
				"down": {"uv": [0.75, 6.75, 0.75, 7], "texture": "#2"}
			}
		},
		{
			"from": [1, 0, 13],
			"to": [1.2, 1, 14],
			"rotation": {"x": 0, "y": -90, "z": 0, "origin": [1, 0, 13]},
			"faces": {
				"north": {"uv": [0.75, 7, 0.75, 7.25], "texture": "#2"},
				"east": {"uv": [0.5, 7, 0.75, 7.25], "texture": "#2"},
				"south": {"uv": [1, 7, 1, 7.25], "texture": "#2"},
				"west": {"uv": [0.75, 7, 1, 7.25], "texture": "#2"},
				"up": {"uv": [0.75, 7, 0.75, 6.75], "texture": "#2"},
				"down": {"uv": [0.75, 6.75, 0.75, 7], "texture": "#2"}
			}
		},
		{
			"from": [15, 0, 13],
			"to": [15.2, 1, 14],
			"rotation": {"x": 0, "y": -90, "z": 0, "origin": [15, 0, 13]},
			"faces": {
				"north": {"uv": [0.75, 7, 0.75, 7.25], "texture": "#2"},
				"east": {"uv": [0.5, 7, 0.75, 7.25], "texture": "#2"},
				"south": {"uv": [1, 7, 1, 7.25], "texture": "#2"},
				"west": {"uv": [0.75, 7, 1, 7.25], "texture": "#2"},
				"up": {"uv": [0.75, 7, 0.75, 6.75], "texture": "#2"},
				"down": {"uv": [0.75, 6.75, 0.75, 7], "texture": "#2"}
			}
		},
		{
			"from": [0, 0, 12],
			"to": [0.1, 1, 19],
			"rotation": {"x": 0, "y": -180, "z": 0, "origin": [0, 0, 12]},
			"faces": {
				"north": {"uv": [11, 9.25, 11, 9.5], "texture": "#2"},
				"east": {"uv": [9.25, 9.25, 11, 9.5], "texture": "#2"},
				"south": {"uv": [12.75, 9.25, 12.75, 9.5], "texture": "#2"},
				"west": {"uv": [11, 9.25, 12.75, 9.5], "texture": "#2"},
				"up": {"uv": [11, 9.25, 11, 7.5], "texture": "#2"},
				"down": {"uv": [11, 7.5, 11, 9.25], "texture": "#2"}
			}
		},
		{
			"from": [15, 0, 5],
			"to": [15.1, 1, 12],
			"rotation": {"angle": 0, "axis": "y", "origin": [15, 0, 5]},
			"faces": {
				"north": {"uv": [11, 9.25, 11, 9.5], "texture": "#2"},
				"east": {"uv": [9.25, 9.25, 11, 9.5], "texture": "#2"},
				"south": {"uv": [12.75, 9.25, 12.75, 9.5], "texture": "#2"},
				"west": {"uv": [11, 9.25, 12.75, 9.5], "texture": "#2"},
				"up": {"uv": [11, 9.25, 11, 7.5], "texture": "#2"},
				"down": {"uv": [11, 7.5, 11, 9.25], "texture": "#2"}
			}
		}
	],
	"display": {
		"thirdperson_righthand": {
			"rotation": [107, 0, 0],
			"translation": [-2.5, 1.5, 6],
			"scale": [0.5, 0.5, 0.5]
		},
		"thirdperson_lefthand": {
			"rotation": [107, 0, 0],
			"translation": [-2.5, 1.5, 6],
			"scale": [0.5, 0.5, 0.5]
		},
		"firstperson_righthand": {
			"rotation": [69, 0, 0],
			"translation": [1.5, 7.5, 5.25]
		},
		"firstperson_lefthand": {
			"rotation": [69, 0, 0],
			"translation": [1.5, 7.5, 5.25]
		},
		"ground": {
			"translation": [0, 4, 0],
			"scale": [0.5, 0.5, 0.5]
		},
		"gui": {
			"rotation": [90, 0, 0]
		},
		"fixed": {
			"rotation": [-90, 0, 0],
			"translation": [0, 0, -7.5]
		}
	},
	"groups": [
		0,
		{
			"name": "TopFrame",
			"origin": [8, 8, 8],
			"scope": 0,
			"color": 0,
			"children": [1, 2, 3, 4]
		},
		{
			"name": "SideFrame",
			"origin": [8, 8, 8],
			"scope": 0,
			"color": 0,
			"children": [5, 6, 7, 8, 9, 10, 11, 12, 13, 14]
		}
	]
}